rcutils/_dummy.cpython-310-x86_64-linux-gnu.so
ros_rcutils-6.9.8.data/data/include/rcutils/rcutils/allocator.h
ros_rcutils-6.9.8.data/data/include/rcutils/rcutils/cmdline_parser.h
ros_rcutils-6.9.8.data/data/include/rcutils/rcutils/env.h
ros_rcutils-6.9.8.data/data/include/rcutils/rcutils/error_handling.h
ros_rcutils-6.9.8.data/data/include/rcutils/rcutils/filesystem.h
ros_rcutils-6.9.8.data/data/include/rcutils/rcutils/find.h
ros_rcutils-6.9.8.data/data/include/rcutils/rcutils/format_string.h
ros_rcutils-6.9.8.data/data/include/rcutils/rcutils/isalnum_no_locale.h
ros_rcutils-6.9.8.data/data/include/rcutils/rcutils/join.h
ros_rcutils-6.9.8.data/data/include/rcutils/rcutils/logging.h
ros_rcutils-6.9.8.data/data/include/rcutils/rcutils/logging_macros.h
ros_rcutils-6.9.8.data/data/include/rcutils/rcutils/macros.h
ros_rcutils-6.9.8.data/data/include/rcutils/rcutils/process.h
ros_rcutils-6.9.8.data/data/include/rcutils/rcutils/qsort.h
ros_rcutils-6.9.8.data/data/include/rcutils/rcutils/repl_str.h
ros_rcutils-6.9.8.data/data/include/rcutils/rcutils/sha256.h
ros_rcutils-6.9.8.data/data/include/rcutils/rcutils/shared_library.h
ros_rcutils-6.9.8.data/data/include/rcutils/rcutils/snprintf.h
ros_rcutils-6.9.8.data/data/include/rcutils/rcutils/split.h
ros_rcutils-6.9.8.data/data/include/rcutils/rcutils/stdatomic_helper.h
ros_rcutils-6.9.8.data/data/include/rcutils/rcutils/strcasecmp.h
ros_rcutils-6.9.8.data/data/include/rcutils/rcutils/strdup.h
ros_rcutils-6.9.8.data/data/include/rcutils/rcutils/strerror.h
ros_rcutils-6.9.8.data/data/include/rcutils/rcutils/time.h
ros_rcutils-6.9.8.data/data/include/rcutils/rcutils/types.h
ros_rcutils-6.9.8.data/data/include/rcutils/rcutils/visibility_control.h
ros_rcutils-6.9.8.data/data/include/rcutils/rcutils/visibility_control_macros.h
ros_rcutils-6.9.8.data/data/include/rcutils/rcutils/stdatomic_helper/gcc/stdatomic.h
ros_rcutils-6.9.8.data/data/include/rcutils/rcutils/stdatomic_helper/win32/stdatomic.h
ros_rcutils-6.9.8.data/data/lib/python3.10/site-packages/rcutils-6.9.8-py3.10.egg-info/PKG-INFO
ros_rcutils-6.9.8.data/data/lib/python3.10/site-packages/rcutils-6.9.8-py3.10.egg-info/SOURCES.txt
ros_rcutils-6.9.8.data/data/lib/python3.10/site-packages/rcutils-6.9.8-py3.10.egg-info/dependency_links.txt
ros_rcutils-6.9.8.data/data/lib/python3.10/site-packages/rcutils-6.9.8-py3.10.egg-info/top_level.txt
ros_rcutils-6.9.8.dist-info/METADATA
ros_rcutils-6.9.8.dist-info/WHEEL
ros_rcutils-6.9.8.dist-info/top_level.txt
ros_rcutils-6.9.8.dist-info/RECORD
ros_rcutils-6.9.8.dist-info/licenses/LICENSE
