Metadata-Version: 2.4
Name: ros-rcutils
Version: 6.9.8
Summary: rcutils is a ROS 2 C API package offering fundamental utility functions and data structures for the ROS 2 codebase.
License-File: LICENSE
Dynamic: description
Dynamic: description-content-type
Dynamic: license-file
Dynamic: summary
